whizbang/__init__.py
whizbang/__main__.py
whizbang/config/__init__.py
whizbang/config/app_config.json
whizbang/config/app_config.py
whizbang/config/deployConfig.json
whizbang/config/environment_config.py
whizbang/config/lab_test_environment_config.json
whizbang/config/test_environment_config.json
whizbang/container/application_container.py
whizbang/core/context_factory_base.py
whizbang/core/context_factory_repository_base.py
whizbang/core/context_manager_base.py
whizbang/core/manager_base.py
whizbang/core/workflow.py
whizbang/core/workflow_task.py
whizbang/data/api_context.py
whizbang/data/az_cli_context.py
whizbang/data/az_cli_response.py
whizbang/data/data_container.py
whizbang/data/databricks/databricks_api_types.py
whizbang/data/databricks/databricks_client_args.py
whizbang/data/databricks/databricks_cluster_context.py
whizbang/data/databricks/databricks_context_base.py
whizbang/data/databricks/databricks_context_factory.py
whizbang/data/databricks/databricks_filesystem_context.py
whizbang/data/databricks/databricks_job_context.py
whizbang/data/databricks/databricks_library_context.py
whizbang/data/databricks/databricks_pool_context.py
whizbang/data/databricks/databricks_secret_context.py
whizbang/data/databricks/databricks_sql_endpoint_context.py
whizbang/data/databricks/databricks_token_context.py
whizbang/data/databricks/databricks_workspace_context.py
whizbang/data/pyodbc/pyodbc_context.py
whizbang/data/pyodbc/pyodbc_context_args.py
whizbang/data/pyodbc/pyodbc_context_factory.py
whizbang/deploy.py
whizbang/domain/exceptions.py
whizbang/domain/handler/account_handler.py
whizbang/domain/handler/active_directory_handler.py
whizbang/domain/handler/app_registration_handler.py
whizbang/domain/handler/bicep_handler.py
whizbang/domain/handler/container_registry_handler.py
whizbang/domain/handler/databricks_handler.py
whizbang/domain/handler/datafactory_handler.py
whizbang/domain/handler/handler_base.py
whizbang/domain/handler/handler_container.py
whizbang_deployer-1.3.0a660.dist-info/entry_points.txt
whizbang_deployer-1.3.0a660.dist-info/LICENSE
whizbang_deployer-1.3.0a660.dist-info/WHEEL
whizbang_deployer-1.3.0a660.dist-info/METADATA
whizbang_deployer-1.3.0a660.dist-info/RECORD
