Metadata-Version: 2.1
Name: whizbang-deployer
Version: 1.3.0a660
Summary: Whizbang Deployer - An all-in-one Azure deployment solution
Home-page: https://github.com/hitachisolutionsamerica/whizbang-deployer
License: MIT
Author: Brian Aiken
Author-email: baiken@hitachisolutions.com
Requires-Python: >=3.9,<4.0
Classifier: License :: OSI Approved :: MIT License
Classifier: Programming Language :: Python :: 3
Classifier: Programming Language :: Python :: 3.9
Requires-Dist: az.cli (>=0.5,<0.6)
Requires-Dist: azure-cli (>=2.30.0,<3.0.0)
Requires-Dist: databricks-cli (==0.17.4)
Requires-Dist: dependency-injector (>=4.35.2,<5.0.0)
Requires-Dist: jsonpath-ng (>=1.5.3,<2.0.0)
Requires-Dist: pydantic (>=1.8.2,<2.0.0)
Requires-Dist: pyodbc (>=4.0.32,<5.0.0)
Requires-Dist: pytest (>=6.2.4,<8.0.0)
Requires-Dist: sqlparse (>=0.4.1,<0.5.0)
Project-URL: Repository, https://github.com/hitachisolutionsamerica/whizbang-deployer
